mooch/__init__.py
mooch/banktransfer.py
mooch/base.py
mooch/mail.py
mooch/models.py
mooch/postfinance.py
mooch/signals.py
mooch/stripe.py
mooch/locale/de/LC_MESSAGES/django.mo
mooch/locale/de/LC_MESSAGES/django.po
mooch/templates/mooch/banktransfer_payment_form.html
mooch/templates/mooch/postfinance_payment_form.html
mooch/templates/mooch/stripe_payment_form.html
mooch/templates/mooch/thanks_mail.txt
django_mooch-0.6.0.dist-info/LICENSE
django_mooch-0.6.0.dist-info/METADATA
django_mooch-0.6.0.dist-info/WHEEL
django_mooch-0.6.0.dist-info/top_level.txt
django_mooch-0.6.0.dist-info/RECORD
