Metadata-Version: 2.1
Name: django-mooch
Version: 0.6.0
Summary: Simple payment for Django
Home-page: https://github.com/matthiask/django-mooch/
Author: Matthias Kestenholz
Author-email: mk@feinheit.ch
License: MIT
Platform: OS Independent
Classifier: Development Status :: 4 - Beta
Classifier: Environment :: Web Environment
Classifier: Framework :: Django
Classifier: Intended Audience :: Developers
Classifier: License :: OSI Approved :: BSD License
Classifier: License :: OSI Approved :: MIT License
Classifier: Operating System :: OS Independent
Classifier: Programming Language :: Python
Classifier: Programming Language :: Python :: 3
Classifier: Topic :: Internet :: WWW/HTTP :: Dynamic Content
Classifier: Topic :: Software Development
Classifier: Topic :: Software Development :: Libraries :: Application Frameworks
License-File: LICENSE
Requires-Dist: requests (>2)
Provides-Extra: tests
Requires-Dist: coverage ; extra == 'tests'
